{
    "Название ЛС": "Фелодипин",
    "Побочные эффекты": {
        "периферический отёк": "Очень часто",
        "астения": "Часто",
        "чувство тепло": "Часто",
        "боль в грудь": "Частота неизвестна",
        "отёк лицо": "Частота неизвестна",
        "заболевание, похожий на грипп": "Частота неизвестна",
        "грипп": "Частота неизвестна",
        "головной боль": "Очень часто",
        "головокружение": "Часто",
        "парестезия": "Часто",
        "обморок": "Частота неизвестна",
        "сонливость": "Частота неизвестна",
        "тошнота": "Часто",
        "диспепсия": "Часто",
        "запор": "Часто",
        "боль в живот": "Частота неизвестна",
        "диарея": "Частота неизвестна",
        "рвота": "Частота неизвестна",
        "сухость в рот": "Частота неизвестна",
        "метеоризм": "Частота неизвестна",
        "кислотный регургитация": "Частота неизвестна",
        "гиперплазия десна": "Частота неизвестна",
        "кашель": "Часто",
        "ринорей": "Часто",
        "чихание": "Часто",
        "одышка": "Частота неизвестна",
        "фарингит": "Частота неизвестна",
        "бронхит": "Частота неизвестна",
        "синусит": "Частота неизвестна",
        "эпистаксис": "Частота неизвестна",
        "респираторный инфекция": "Частота неизвестна",
        "сердцебиение": "Часто",
        "покраснение кожа": "Часто",
        "инфаркт миокард": "Частота неизвестна",
        "гипотония": "Частота неизвестна",
        "стенокардия": "Частота неизвестна",
        "аритмия": "Частота неизвестна",
        "тахикардия": "Частота неизвестна",
        "преждевременный сердечный сокращение": "Частота неизвестна",
        "сыпь": "Часто",
        "ангионевротический образование": "Частота неизвестна",
        "контузия": "Частота неизвестна",
        "эритема": "Частота неизвестна",
        "крапивница": "Частота неизвестна",
        "лейкоцитокластичный васкулит": "Частота неизвестна",
        "артралгия": "Частота неизвестна",
        "боль в спина": "Частота неизвестна",
        "боль в нога": "Частота неизвестна",
        "мышечный спазм": "Частота неизвестна",
        "миалгия": "Частота неизвестна",
        "боль в рука": "Частота неизвестна",
        "боль в колено": "Частота неизвестна",
        "боль в бедро": "Частота неизвестна",
        "бессонница": "Частота неизвестна",
        "депрессия": "Частота неизвестна",
        "тревожный расстройство": "Частота неизвестна",
        "раздражительность": "Частота неизвестна",
        "нервозность": "Частота неизвестна",
        "снижение либидо": "Частота неизвестна",
        "импотенция": "Частота неизвестна",
        "частый мочеиспускание": "Частота неизвестна",
        "немедленный желание мочеиспускание": "Частота неизвестна",
        "дизурия": "Частота неизвестна",
        "полиурия": "Частота неизвестна",
        "гинекомастие": "Частота неизвестна",
        "анемия": "Частота неизвестна",
        "увеличение алта": "Частота неизвестна",
        "нарушение зрение": "Частота неизвестна"
    }
}