{
    "Название ЛС": "Кандесартан",
    "Побочные действия": {
        "Со стороны дыхательной системы": {
            "Часто": [
                "инфекция верхних дыхательных путей",
                "фарингит",
                "ринит",
                "назофарингит"
            ],
            "Очень редко": [
                "кашель"
            ]
        },
        "Со стороны почек": {
            "Часто": [
                "нарушения функции почек",
                "увеличение креатинина",
                "увеличение уровня мочевина"
            ]
        },
        "Со стороный нервной системы": {
            "Часто": [
                "головокружение",
                "головная боль"
            ],
            "Очень редко": [
                "сонливость"
            ]
        },
        "Со стороны сердечно-сосудистой системы": {
            "Часто": [
                "гипотония",
                "синусовая аритмия"
            ],
            "Очень редко": [
                "Тахикардия"
            ]
        },
        "Со стороны печени": {
            "Часто": [
                "увеличение АЛТ"
            ],
            "Не часто": [
                "нарушение функций печени",
                "повышенный уровень АСТ"
            ],
            "Очень редко": [
                "гепатит"
            ]
        },
        "Со стороны метаболизма": {
            "Часто": [
                "гиперкалиемия"
            ],
            "Не часто": [
                "гипонатриемия"
            ]
        },
        "Со стороны опорно-двигательной системы": {
            "Часто": [
                "боль в спине"
            ],
            "Очень редко": [
                "Артралгия",
                "миалгия"
            ],
            "Часто неизвеста": [
                "рабдомиолиз"
            ]
        },
        "Со стороны кожных покровов и подкожных тканей": {
            "Часто": [
                "сыпь"
            ],
            "Очень редко": [
                "зуд",
                "крапивница"
            ]
        },
        "Другие побочные действия": {
            "Часто": [
                "пирексия"
            ]
        },
        "Со стороны психики": {
            "Очень редко": [
                "Ажитация",
                "тревожность",
                "депрессия",
                "бессонница",
                "нервозность",
                "кошмары",
                "расстройство сна"
            ]
        },
        "Со стороны кровеносной системы": {
            "Очень редко": [
                "нейтропения",
                "лейкопения",
                "Агранулоцитоз"
            ]
        },
        "Со стороны желудочно-кишечного тракта": {
            "Очень редко": [
                "тошнота"
            ],
            "Часто неизвеста": [
                "ороглоточная боль"
            ]
        },
        "Со стороны иммунной системы": {
            "Очень редко": [
                "Ангионевротическое образование"
            ]
        }
    }
}